palgate_py/__about__.py
palgate_py/__init__.py
palgate_py/__main__.py
palgate_py/py.typed
palgate_py/cli/__init__.py
palgate_py/cli/cli.py
palgate_py/palgate/__init__.py
palgate_py/palgate/config.py
palgate_py/palgate/models.py
palgate_py/palgate/palgate.py
palgate_py-0.0.4.dist-info/METADATA
palgate_py-0.0.4.dist-info/WHEEL
palgate_py-0.0.4.dist-info/entry_points.txt
palgate_py-0.0.4.dist-info/licenses/LICENSE.txt
palgate_py-0.0.4.dist-info/RECORD
