Metadata-Version: 2.4
Name: palgate-py
Version: 0.0.4
Project-URL: Documentation, https://github.com/omercnet/palgate-py#readme
Project-URL: Issues, https://github.com/omercnet/palgate-py/issues
Project-URL: Source, https://github.com/omercnet/palgate-py
Author-email: omercnet <639682+omercnet@users.noreply.github.com>
License-Expression: MIT
License-File: LICENSE.txt
Classifier: Development Status :: 4 - Beta
Classifier: Programming Language :: Python
Classifier: Programming Language :: Python :: 3.9
Classifier: Programming Language :: Python :: 3.10
Classifier: Programming Language :: Python :: 3.11
Classifier: Programming Language :: Python :: 3.12
Classifier: Programming Language :: Python :: Implementation :: CPython
Classifier: Programming Language :: Python :: Implementation :: PyPy
Requires-Python: >=3.9
Requires-Dist: click
